<?xml version="1.0" encoding="utf-8" ?>
<c2eventsheet>
    <!--All the 'name' attributes are ignored by Construct 2 - they are there for readability only.-->
    <name>Tried mechanics</name>
    <events>
        <event-block sid="1974162530078484">
            <conditions>
                <condition id="-14" name="Compare variable" sid="4069544281325267" type="System">
                    <param id="0" name="Variable">EnemyState</param>
                    <param id="1" name="Comparison">0</param>
                    <param id="2" name="Value">4</param>
                </condition>
            </conditions>
            <actions>
                <action id="-16" name="Wait" sid="7571396751633744" type="System">
                    <param id="0" name="Seconds">1</param>
                </action>
                <action behavior="Rotate" id="0" name="Set speed" sid="5808763316598388" type="center">
                    <param id="0" name="Speed">0</param>
                </action>
            </actions>
        </event-block>
        <event-block sid="9215731413961489">
            <conditions>
                <condition id="-14" name="Compare variable" sid="8814662804292658" type="System">
                    <param id="0" name="Variable">EnemyState</param>
                    <param id="1" name="Comparison">0</param>
                    <param id="2" name="Value">4</param>
                </condition>
            </conditions>
            <actions>
                <action id="-16" name="Wait" sid="3984952924489305" type="System">
                    <param id="0" name="Seconds">1</param>
                </action>
                <action id="0" name="Spawn another object" sid="2594702736443056" type="center">
                    <param id="0" name="Object">slowerBullet</param>
                    <param id="1" name="Layer">0</param>
                    <param id="2" name="Image point">0</param>
                </action>
                <action id="-19" name="Rotate counter-clockwise" sid="7447546881637236" type="center">
                    <param id="0" name="Degrees">180</param>
                </action>
                <action id="0" name="Spawn another object" sid="9593562837203226" type="center">
                    <param id="0" name="Object">slowerBullet</param>
                    <param id="1" name="Layer">0</param>
                    <param id="2" name="Image point">0</param>
                </action>
                <action id="-16" name="Wait" sid="9899834093375735" type="System">
                    <param id="0" name="Seconds">0.5</param>
                </action>
                <action id="-19" name="Rotate counter-clockwise" sid="3423267931308929" type="center">
                    <param id="0" name="Degrees">90</param>
                </action>
                <action id="0" name="Spawn another object" sid="3681484227870318" type="center">
                    <param id="0" name="Object">slowerBullet</param>
                    <param id="1" name="Layer">0</param>
                    <param id="2" name="Image point">0</param>
                </action>
                <action id="-19" name="Rotate counter-clockwise" sid="6100779275778739" type="center">
                    <param id="0" name="Degrees">180</param>
                </action>
                <action id="0" name="Spawn another object" sid="6855073923369782" type="center">
                    <param id="0" name="Object">slowerBullet</param>
                    <param id="1" name="Layer">0</param>
                    <param id="2" name="Image point">0</param>
                </action>
                <action id="-9" name="Set value" sid="7492431475594562" type="System">
                    <param id="0" name="Variable">EnemyState</param>
                    <param id="1" name="Value">0</param>
                </action>
            </actions>
        </event-block>
        <event-block sid="3053284611674335">
            <conditions>
                <condition id="-2" name="On start of layout" sid="3781503067276901" type="System" />
            </conditions>
            <actions>
                <action id="5" name="Set web font" sid="9606431109070079" type="dummyFont">
                    <param id="0" name="Family name">&quot;plasticineregular&quot;</param>
                    <param id="1" name="CSS URL">&quot;https://dl.dropboxusercontent.com/u/78679641/City%20Hero/Font/stylesheet.css&quot;</param>
                </action>
            </actions>
        </event-block>
    </events>
</c2eventsheet>
